emot/__init__.py
emot/core.py
emot/emo_unicode.py
emot/pattern_generator.py
emot/test.py
emot-3.0.dist-info/LICENSE
emot-3.0.dist-info/METADATA
emot-3.0.dist-info/WHEEL
emot-3.0.dist-info/top_level.txt
emot-3.0.dist-info/zip-safe
emot-3.0.dist-info/RECORD
