Metadata-Version: 2.1
Name: emot
Version: 3.0
Summary: Emoji and Emoticons detection package for Python
Home-page: https://github.com/NeelShah18/emo
Author: Neel Shah
Author-email: neelknightme@gmail.com
License: GNU GENERAL PUBLIC LICENSE
Download-URL: https://github.com/NeelShah18/emot/archive/refs/tags/v3.0.tar.gz
Keywords: emoji, emoticons
Platform: UNKNOWN
License-File: LICENSE
